burstH2MM/BurstSort.py
burstH2MM/Masking.py
burstH2MM/ModelError.py
burstH2MM/Plotting.py
burstH2MM/Simulations.py
burstH2MM/__init__.py
burstH2MM-0.1.7.dist-info/LICENSE.txt
burstH2MM-0.1.7.dist-info/METADATA
burstH2MM-0.1.7.dist-info/WHEEL
burstH2MM-0.1.7.dist-info/top_level.txt
burstH2MM-0.1.7.dist-info/RECORD
