Metadata-Version: 2.1
Name: burstH2MM
Version: 0.1.7
Summary: API for using H2MM_C with FRETBursts
Home-page: https://github.com/harripd/burstH2MM
Author: Paul David Harris
Author-email: paul.harris@mail.huji.ac.il
Project-URL: Bug Tracker, https://github.com/harripd/burstH2MM
Classifier: Programming Language :: Python
Classifier: License :: OSI Approved :: MIT License
Classifier: Intended Audience :: Science/Research
Classifier: Operating System :: OS Independent
Classifier: Topic :: Scientific/Engineering
Classifier: Intended Audience :: Science/Research
Requires-Python: >=3.8
License-File: LICENSE.txt
Requires-Dist: numpy (>=1.20.1)
Requires-Dist: h2mm-c (>=1.0.3)
